{
    "proposal": {
        "arguable": true, 
        "author": null, 
        "author_id": null, 
        "can_hide": false, 
        "can_hide_author": false, 
        "category": {
            "id": 1, 
            "name": "Bon viure"
        }, 
        "closed": true, 
        "code": "BCN-2016-04-9095", 
        "conflictive": false, 
        "created_at": "07/04/2016", 
        "district": null, 
        "editable": false, 
        "external_url": "", 
        "flagged": null, 
        "from_meeting": true, 
        "hidden": false, 
        "id": 9095, 
        "official": false, 
        "permissions": {
            "comment": false, 
            "comment_as_administrator": false, 
            "comment_as_moderator": false
        }, 
        "scope_": "city", 
        "social_media_image_url": "https://decidim.barcelona/assets/social-media-icon-1bdc8642dd06be182477369bbb1bd5399cd7dda6aefeab4b1d1a9693cce26838.png", 
        "source": "meeting", 
        "status": "accepted", 
        "subcategory": {
            "category_id": 1, 
            "id": 1, 
            "name": "Just\u00edcia social", 
            "position": 1
        }, 
        "summary": "Crear un registre \u00fanic d\u2019ajudes municipals de manera que es pugui saber quina \u00e9s la totalitat d\u2019ajudes que rep una fam\u00edlia o usuari/a.", 
        "title": "Crear un registre \u00fanic d\u2019ajudes municipals ", 
        "total_comments": 0, 
        "total_negative_comments": 0, 
        "total_neutral_comments": 0, 
        "total_positive_comments": 0, 
        "total_votes": 0, 
        "url": "https://decidim.barcelona/pam/proposals/crear-un-registre-unic-d-ajudes-municipals", 
        "votable": null, 
        "voted": null
    }
}