{
    "proposal": {
        "arguable": true, 
        "author": null, 
        "author_id": null, 
        "can_hide": false, 
        "can_hide_author": false, 
        "category": {
            "id": 2, 
            "name": "Economia plural"
        }, 
        "closed": true, 
        "code": "BCN-2016-04-9704", 
        "conflictive": false, 
        "created_at": "08/04/2016", 
        "district": {
            "id": 5, 
            "name": "Sarri\u00e0 - Sant Gervasi"
        }, 
        "editable": false, 
        "external_url": "", 
        "flagged": null, 
        "from_meeting": true, 
        "hidden": false, 
        "id": 9704, 
        "official": false, 
        "permissions": {
            "comment": false, 
            "comment_as_administrator": false, 
            "comment_as_moderator": false
        }, 
        "scope_": "district", 
        "social_media_image_url": "https://decidim.barcelona/assets/social-media-icon-1bdc8642dd06be182477369bbb1bd5399cd7dda6aefeab4b1d1a9693cce26838.png", 
        "source": "meeting", 
        "status": "rejected", 
        "subcategory": {
            "category_id": 2, 
            "id": 10, 
            "name": "Desenvolupament i economia de proximitat", 
            "position": 1
        }, 
        "summary": "Deixar de donar llic\u00e8ncies als Street Markets donat que la gent que comercia es gent de fora que fa un pseudo-mercat de productes d\u2019artesania, que no ho son pas. Aquests tipus de mercats que han emergit en els \u00faltims temps no s\u2019han de confondre amb les mostres de botigues del barri interactuant amb d\u2019altres botiguers i comerciants de la ciutat.", 
        "title": "Llic\u00e8ncies a Street Markets", 
        "total_comments": 0, 
        "total_negative_comments": 0, 
        "total_neutral_comments": 0, 
        "total_positive_comments": 0, 
        "total_votes": 1, 
        "url": "https://decidim.barcelona/pam/proposals/llicencies-a-steet-markets", 
        "votable": null, 
        "voted": null
    }
}